PN_DTW_FE/__init__.py
PN_DTW_FE/calculate_distance_significance.py
PN_DTW_FE/exclude_and_assign_above_threshold.py
PN_DTW_FE/main.py
PN_DTW_FE/main_old.py
PN_DTW_FE/main_old_2.py
PN_DTW_FE/merge_bell_shaped_with_spacers_pandas.py
PN_DTW_FE/optimize_chunks_for_normality_pandas.py
PN_DTW_FE/sort_and_divide_series_into_n_chunks.py
PN_DTW_FE/sort_and_merge_series.py
PN_DTW_FE/tmm.py
PN_DTW_FE-0.10.2.dist-info/LICENSE.txt
PN_DTW_FE-0.10.2.dist-info/METADATA
PN_DTW_FE-0.10.2.dist-info/WHEEL
PN_DTW_FE-0.10.2.dist-info/entry_points.txt
PN_DTW_FE-0.10.2.dist-info/top_level.txt
PN_DTW_FE-0.10.2.dist-info/RECORD
